{"stem":"auseinandersetzungen","instances":[{"docId":"Rundbrief_003","docUri":"Rundbrief_003.html","score":1,"contexts":[{"form":"Auseinandersetzungen","weight":"1","pos":1095,"context":".... Übungsstunden über praktische Bühnen- kunde zunächst grundsätzliche <mark>Auseinandersetzungen<\/mark> über Theater- wissenschaft und Bühnenpraxis in ihrer Polarität...","fid":"p__52"}]},{"docId":"Rundbrief_005","docUri":"Rundbrief_005.html","score":1,"contexts":[{"form":"Auseinandersetzungen","weight":"1","pos":1657,"context":"...Faust (Herterich) in der Studierstube in seinen <mark>Auseinandersetzungen<\/mark> mit Mephistopheles (Eybner) und mit dem bösen...","fid":"p__71"}]}]}