{"stem":"ausländischen","instances":[{"docId":"Rundbrief_001","docUri":"Rundbrief_001.html","score":1,"contexts":[{"form":"ausländischen","weight":"1","pos":505,"context":"...und die Aussprachemöglichkeiten mit jenen Forschern, deutschen und <mark>ausländischen<\/mark>, die am Zentralinstitut arbeiten.","fid":"p__10"}]},{"docId":"Rundbrief_004","docUri":"Rundbrief_004.html","score":1,"contexts":[{"form":"ausländischen","weight":"1","pos":474,"context":"...sich das Theater in der unmittelbaren Auseinandersetzung mit dem <mark>ausländischen<\/mark> Gut zu eigener Höhe entwickelt, Künstler von Rang...","fid":"p__13"}]}]}