{"stem":"ermöglicht","instances":[{"docId":"Rundbrief_004_2","docUri":"Rundbrief_004_2.html","score":3,"contexts":[{"form":"ermöglichte","weight":"1","pos":90,"context":"...Karten pro Vorstellung für die Studenten bekam. Das <mark>ermöglichte<\/mark> nun die Gründung der Arbeitsgemeinschaften: Deutsches Volkstheater,...","fid":"p__12"},{"form":"ermöglicht","weight":"1","pos":978,"context":"...allzu fern sein, die auch wiederum eine persönliche Zusammenarbeit <mark>ermöglicht<\/mark>. Der geistige Austausch","fid":"p__3"},{"form":"ermöglicht","weight":"1","pos":1686,"context":"wird es uns <mark>ermöglicht<\/mark> werden, Ateliers zu besuchen, die Dreharbeit zu beobachten...","fid":"p__27"}]},{"docId":"Rundbrief_005","docUri":"Rundbrief_005.html","score":1,"contexts":[{"form":"ermöglicht","weight":"1","pos":1806,"context":"...Euch, so weit es uns die momentan schwere Kampfphase <mark>ermöglicht<\/mark>, trotzdem ein recht frohes Fest wünschen.","fid":"p__5"}]}]}