{"stem":"gast","instances":[{"docId":"Rundbrief_003","docUri":"Rundbrief_003.html","score":1,"contexts":[{"form":"Gast","weight":"1","pos":2750,"context":"Als <mark>Gast<\/mark> des Zentralinstituts sprach am 18. Februar Prof. Dr....","fid":"p__105"}]},{"docId":"Rundbrief_004_2","docUri":"Rundbrief_004_2.html","score":1,"contexts":[{"form":"Gast","weight":"1","pos":1711,"context":"...der folgenden Ringvorlesung empfingen wir im Institut wieder einen <mark>Gast<\/mark>: den Chefdramaturgen des Nationaltheaters in Weimar und Inhaber...","fid":"p__35"}]}]}