{"stem":"gelenkt","instances":[{"docId":"Rundbrief_003","docUri":"Rundbrief_003.html","score":1,"contexts":[{"form":"gelenkte","weight":"1","pos":3055,"context":"...reiche Theatererfahrung und der von eigener dichterischer In- tuition <mark>gelenkte<\/mark> Blick befähigen Wurm, allen charakteristischen Schat- tierungen...","fid":"p__117"}]},{"docId":"Rundbrief_001","docUri":"Rundbrief_001.html","score":1,"contexts":[{"form":"gelenkt","weight":"1","pos":1128,"context":"...ja die Forschungsarbeit der jungen Generation in gute Bahnen <mark>gelenkt<\/mark> werden. Dieses Reallexikon wird als Veröffentlichung des Zentralinstituts erscheinen...","fid":"p__19"}]}]}