{"stem":"luft","instances":[{"docId":"Rundbrief_003","docUri":"Rundbrief_003.html","score":1,"contexts":[{"form":"Luft","weight":"1","pos":2312,"context":"...Begriff sind, die Festung und sich selbst in die <mark>Luft<\/mark> zu sprengen, weil sie keinen anderen Ausweg sehen...","fid":"p__118"}]},{"docId":"Rundbrief_005","docUri":"Rundbrief_005.html","score":1,"contexts":[{"form":"Luft","weight":"1","pos":1634,"context":".... Auf einem gefl체gelten Drachen f채hrt er durch die <mark>Luft<\/mark> und f체hrt den Grossen der Erde seine K체nste vor....","fid":"p__71"}]}]}