{"stem":"nahezukommen","instances":[{"docId":"Rundbrief_001","docUri":"Rundbrief_001.html","score":2,"contexts":[{"form":"nahezukommen","weight":"1","pos":1338,"context":"...zu verstehen und ihr soweit als möglich auch wissenschaftlich <mark>nahezukommen<\/mark>. Es ist also nur selbstverständlich, daß Wien...","fid":"p__13"},{"form":"nahezukommen","weight":"1","pos":1747,"context":".... 13 endlichen Räumlichen und Zeitlichen als dem Ewigen <mark>nahezukommen<\/mark>, so vereint eben das Theater schon in seiner...","fid":"p__15"}]}]}