{"stem":"raimund","instances":[{"docId":"Rundbrief_001","docUri":"Rundbrief_001.html","score":1,"contexts":[{"form":"Raimund","weight":"1","pos":289,"context":"...der Assistentinnen ist nach dem großen Volksdarsteller und Volksdramatiker <mark>Raimund<\/mark>, das Direktorzimmer nach dem Burgtheaterdirektor Freiherrn von Berger...","fid":"p__19"}]},{"docId":"Rundbrief_004","docUri":"Rundbrief_004.html","score":1,"contexts":[{"form":"Raimund","weight":"1","pos":909,"context":"..., Goethe, Schiller, Kleist, Grillparzer, <mark>Raimund<\/mark>, Hebbel, Gerhart Hauptmann im Burgtheater. Wieder...","fid":"p__13"}]},{"docId":"Rundbrief_002","docUri":"Rundbrief_002.html","score":1,"contexts":[{"form":"Raimund","weight":"1","pos":272,"context":"...Kindermanns Biographie über den Wiener Volksdramatiker und Volksdarsteller Ferdinand <mark>Raimund<\/mark> im Wiener Verlag, Wien, XII., Niederhofstraße...","fid":"p__30"}]}]}