{"stem":"schiffer","instances":[{"docId":"Rundbrief_003","docUri":"Rundbrief_003.html","score":1,"contexts":[{"form":"Schiffer","weight":"1","pos":3740,"context":"...bisherigen bewährten Assistentinnen Frl. Dietrich und Frl. <mark>Schiffer<\/mark> noch die schon erwähnte Verwalterin des Leuschke-Archivs...","fid":"p__165"}]},{"docId":"Rundbrief_001","docUri":"Rundbrief_001.html","score":1,"contexts":[{"form":"Schiffer","weight":"1","pos":107,"context":"...wissenschaftliche Hilfskräfte, Fräulein Margret Dietrich und Fräulein Gustave <mark>Schiffer<\/mark>, zur Seite. Ein ganzer Stab von reiferen...","fid":"p__13"}]},{"docId":"Rundbrief_002","docUri":"Rundbrief_002.html","score":1,"contexts":[{"form":"Schiffer","weight":"1","pos":191,"context":"...beiden Assistentinnen, Frl. Dietrich und Frl. <mark>Schiffer<\/mark>, sowie mit Herrn Ulrich, den der Verlag...","fid":"p__17"}]}]}