{"stem":"spezifischen","instances":[{"docId":"Rundbrief_003","docUri":"Rundbrief_003.html","score":2,"contexts":[{"form":"spezifischen","weight":"1","pos":649,"context":"...hundert wurzelt, in ihrem künstlerischen Entwicklungsgang, ihrer <mark>spezifischen<\/mark> Eigenart und ihrem Beitrag zur Gesamtentwicklung der Schauspielkunst analysiert...","fid":"p__33"},{"form":"spezifischen","weight":"1","pos":2102,"context":"..., sondern in einer lebendigen Kommunikation mit den ganz <mark>spezifischen<\/mark> Möglichkeiten des betreffenden Sängers arbeitet. Also statt Starrheit...","fid":"p__102"}]}]}