{"stem":"the","instances":[{"docId":"Rundbrief_003","docUri":"Rundbrief_003.html","score":2,"contexts":[{"form":"\"The","weight":"1","pos":3584,"context":"...Forscher sehr eifrig gearbeitet. Der zweite Band der <mark>\"The<\/mark>- atergeschichte des deutschen Volkes\" ist schon im Umbruch...","fid":"p__166"},{"form":"The","weight":"1","pos":3976,"context":"...Zusammenarbeit zwischen den verschiedenen Instituten ergeben: Zwischen den <mark>The<\/mark>- aterwissenschaftlern, den Bühnengestaltern, den Architekten und...","fid":"p__12"}]},{"docId":"Rundbrief_004","docUri":"Rundbrief_004.html","score":1,"contexts":[{"form":"The","weight":"1","pos":833,"context":"...und Zu- sammenfassung des Professors abgeschlossen wurden. Bei den <mark>The<\/mark>- men ging es zunächst um die Hauptetappen der...","fid":"p__13"}]}]}