{"stem":"tragödien","instances":[{"docId":"Rundbrief_005","docUri":"Rundbrief_005.html","score":1,"contexts":[{"form":"Tragödien","weight":"1","pos":509,"context":"...der Lutherischen Reformation und von all den hunderten von <mark>Tragödien<\/mark> weit überboten. Aber gerade in diese Schwänke und...","fid":"p__10"}]},{"docId":"Rundbrief_004","docUri":"Rundbrief_004.html","score":1,"contexts":[{"form":"Tragödien","weight":"1","pos":320,"context":"..., schreiben die Texte der Komödien, Satyrspiele und <mark>Tragödien<\/mark> und spannen mit ihrem Stoff einen weltweiten Bogen vom...","fid":"p__13"}]}]}