{"stem":"untergebracht","instances":[{"docId":"Rundbrief_001","docUri":"Rundbrief_001.html","score":2,"contexts":[{"form":"untergebracht","weight":"1","pos":151,"context":"...Zentralinstitut für Theaterwissenschaft ist im Reichskanzleitrakt der Wiener Hofburg <mark>untergebracht<\/mark> (fünf Minuten von der Universität entfernt). Es verdankt...","fid":"p__19"},{"form":"untergebracht","weight":"1","pos":279,"context":"...im selben Trakt der Hofburg (ein Stockwerk höher) <mark>untergebracht<\/mark> ist. Die beiden Bibliothekssäle des Zentralinstituts sind nach Mitterwurzer...","fid":"p__19"}]}]}