{"stem":"vision","instances":[{"docId":"Rundbrief_004_2","docUri":"Rundbrief_004_2.html","score":2,"contexts":[{"form":"Vision","weight":"1","pos":1311,"context":"...für Philosophen bestimmt sei. Beim Gestalt-Werden einer dichterischen <mark>Vision<\/mark> auf der Bühne stellt der Geist der Dichtung den...","fid":"p__26"},{"form":"Vision","weight":"1","pos":1346,"context":"...und kann nie ungeistig sein. Er muß eine objektive <mark>Vision<\/mark> des Ganzen haben und mehr zensorisch als motorisch veranlagt...","fid":"p__26"}]}]}