{"stem":"wichtigkeit","instances":[{"docId":"Rundbrief_003","docUri":"Rundbrief_003.html","score":2,"contexts":[{"form":"Wichtigkeit","weight":"1","pos":1101,"context":"...wissenschaft und Bühnenpraxis in ihrer Polarität und stellte die <mark>Wichtigkeit<\/mark> und Notwendigkeit ihrer wechselseitigen Ergänzung dar.","fid":"p__52"},{"form":"Wichtigkeit","weight":"1","pos":4008,"context":"...war Herrn Prof. Kindermanns Vortrag von be- sonderer <mark>Wichtigkeit<\/mark>. Den sog. Kritiker nennen wir heute lieber...","fid":"p__27"}]}]}